{
  "stages": [
    {
      "stage": "awareness",
      "questions": [
        "ביטוח סיעוד מה זה ואיך יודעים אם זכאי",
        "כמשפחה איך יודעים אם ההורה זכאי לביטוח סיעוד",
        "מה ההבדל בין בעיות תפקוד לאלצהיימר בביטוח סיעוד",
        "למה חברת הביטוח דוחה תביעה סיעוד",
        "איך מגישים תביעת ביטוח סיעוד צעד צעד",
        "מה הזכויות שלי כמבוטח מול חברת הביטוח",
        "מתי צריך עורך דין לביטוח סיעוד",
        "איך מוכיחים בעיות תפקוד לחברת ביטוח",
        "חברת ביטוח לא מכירה באלצהיימר מה עושים",
        "כמטפל איך מתמודדים עם דחיית תביעה"
      ],
      "content_needs": [
        "מדריך מפורט זכויות המבוטח בביטוח סיעוד",
        "צ'קליסט תנאי זכאות לביטוח סיעוד",
        "מדריך הוכחת מצב תפקודי מול חברות ביטוח",
        "FAQ משפטי תהליך הגשת תביעות סיעוד",
        "מדריך זכויות משפטיות מול הראל מנורה מגדל",
        "מדריך משפטי דיני ביטוח סיעודי בישראל",
        "רשימת אזהרות דחיית תביעות סיעוד",
        "מדריך ספציפי אלצהיימר פרקינסון דמנציה ביטוח",
        "טמפלט הוכחת זכאות לביטוח סיעוד"
      ]
    },
    {
      "stage": "consideration",
      "questions": [
        "איך לבחור עורך דין לביטוח סיעוד",
        "כמה עולה עורך דין לתביעת ביטוח סיעוד",
        "איך לבחור בין עורכי דין לביטוח סיעוד",
        "כמשפחה איך לבדוק ניסיון עורך דין מול הראל",
        "עורכי דין ביטוח סיעוד המלצות ומה לבדוק",
        "איך נראה עבודה עם עורך דין ביטוח סיעוד",
        "המלצות על עורכי דין ביטוח סיעוד בישראל",
        "כמטפל איך לבחור עורך דין שמבין אותנו",
        "יתרונות עורך דין שמרצה ביטוח סיעוד"
      ],
      "content_needs": [
        "טבלת השוואה איך לבחור עורך דין ביטוח סיעוד",
        "סיפורי הצלחה ניצחונות משפטיים מול הראל מנורה",
        "אוסף המלצות ועדויות לקוחות משפחות",
        "מדריך תהליך עבודה עם עורך דין ביטוח",
        "מחשבון עלויות ושכר טרחה עורכי דין",
        "נתוני הצלחה עורך דין משה תבו מול חברות ביטוח",
        "מדריך השוואת ניסיון עורכי דין ביטוח סיעוד",
        "מדריך בחירת ייצוג משפטי רגיש ומקצועי"
      ]
    },
    {
      "stage": "decision",
      "questions": [
        "איך ליצור קשר עם עורך דין משה תבו",
        "כמשפחה מה להכין לפגישה ראשונה עם עורך דין",
        "כמה זמן לוקח תביעת ביטוח סיעוד",
        "מה הסיכויים לזכות בתביעה מול מנורה הראל",
        "איך משלמים לעורך דין ביטוח סיעוד",
        "מה קורה אם מפסידים בתביעה",
        "איך עורך דין משה תבו יעזור לי בדיוק",
        "מתי יכול להתחיל תהליך עם עורך דין",
        "כמטפל איך מבטיחים שירות אישי ומענה",
        "רשימת מסמכים לתביעת ביטוח סיעוד"
      ],
      "content_needs": [
        "טופס יצירת קשר ותיאום פגישה ראשונה",
        "צ'קליסט מסמכים נדרשים לפגישה ראשונה",
        "מדריך תנאי התקשרות ותשלום שכר טרחה",
        "תהליך עבודה מפורט עורך דין משה תבו",
        "פירוט שירותים והתמחות ביטוח סיעוד",
        "פרטי יצירת קשר וזמינות למשפחות",
        "דף נחיתה יצירת קשר מיידי",
        "לוח זמנים צפוי לתהליך משפטי",
        "הבטחת שירות אישי ומענה מהיר למשפחות",
        "מדריך הכנה מיידית להגשת תביעה"
      ]
    }
  ],
  "_meta": {
    "schema_version": "1.0.0",
    "produced_by": "customer_journey",
    "timestamp": "2025-09-08T00:00:00Z"
  }
}
